[
    {
        "id": "1",
        "name": "James",
        "ratings": 4,
         "comments":"My daughter and I purchased 6 of these tops for our 5 week trip to India. We wore them constantly and washed them almost daily. After hand washing and wringing, we simply hung them on a hanger and they dried quickly and wrinkle-free. Even the ribbing around the neck kept it's shape!"      
      
        
      },
    {
        "id": "2",
        "name": "simon",
        "ratings": 4,
         "comments":"I love that you cannot see through this white shirt. It’s is a fairly thicker material. I am 5’5” and weigh 185. I purchased a large hoping it would fit. And it surpassed my expectations."      
      
        
      },
    {
        "id": "3",
        "name": "conni arnold",
        "ratings": 4,
         "comments":"Love these basic T-shirt! I will be ordering more colors. The fabric is super soft and no scratchy tag. The V at the neck is the perfect length and the shirt overall has a great length."      
      
        
      },
    {
        "id": "4",
        "name": "Ellison",
        "ratings": 4,
         "comments":"Perfect fit!!! I’m a 38DD, 5’10” size 16 woman and the XL is true to size. Not to mention did not shrink in the drier. I’m ordering more!!"      
      
        
      },
    {
        "id": "5",
        "name": "James Lemon",
        "ratings": 4,
         "comments":"Purchased XL. I usually go with L or XL. Size 12. I'm 5'9, 175 lbs, 38DD. Loose fit around middle (which I wanted). A tiny bit tight around bust. Probably won't throw in dryer. Nice fabric weight. Not too heavy or too thin."      
      
        
      },
    {
        "id": "6",
        "name": "Mamos",
        "ratings": 4,
         "comments":"Great quality, not see through. I got the small and it fits perfectly-not too tight and not too loose. I'm 5'8 143lbs, waist 28. Neckline is perfect, not too deep."      
      
        
      }
]